RoboDepCheck.py
RoboDepCheck-1.0.dist-info/DESCRIPTION.rst
RoboDepCheck-1.0.dist-info/METADATA
RoboDepCheck-1.0.dist-info/RECORD
RoboDepCheck-1.0.dist-info/WHEEL
RoboDepCheck-1.0.dist-info/metadata.json
RoboDepCheck-1.0.dist-info/top_level.txt
