Metadata-Version: 2.0
Name: RoboDepCheck
Version: 1.0
Summary: Robot Framework Library for OWASP DEPENDENCY CHECKER
Home-page: https://www.github.com/we45/RoboDepCheck
Author: we45
Author-email: info@we45.com
License: MIT
Platform: UNKNOWN
Requires-Dist: docker
Requires-Dist: robotframework (==3.0.4)
